interviewer/__init__.py
interviewer/answerer.py
interviewer/core.py
interviewer/store.py
interviewer/test_answerer.py
interviewer/util.py
deutscher_befrager-0.0.2.dist-info/METADATA
deutscher_befrager-0.0.2.dist-info/WHEEL
deutscher_befrager-0.0.2.dist-info/entry_points.txt
deutscher_befrager-0.0.2.dist-info/top_level.txt
deutscher_befrager-0.0.2.dist-info/RECORD
