Metadata-Version: 2.1
Name: deutscher-befrager
Version: 0.0.2
Summary: CLI Language Learning Tool
Home-page: https://github.com/pypa/sampleproject
Author: Travis Shears
Author-email: t@travisshears.com
License: UNKNOWN
Keywords: command line interface cli python language learning interactive tool
Platform: UNKNOWN
Classifier: Programming Language :: Python :: 3
Classifier: License :: OSI Approved :: MIT License
Classifier: Operating System :: OS Independent
Classifier: Operating System :: MacOS
Requires-Dist: PyYAML
Requires-Dist: Click
